{
    "ID": 0,
    "CreatedAt": "0001-01-01T00:00:00Z",
    "UpdatedAt": "0001-01-01T00:00:00Z",
    "DeletedAt": null,
    "name": "Champion Life Women's Tights, Vertical Logo",
    "currentPrice": 14.7,
    "previousPrice": 0
},
{
    "ID": 0,
    "CreatedAt": "0001-01-01T00:00:00Z",
    "UpdatedAt": "0001-01-01T00:00:00Z",
    "DeletedAt": null,
    "name": "Lenovo ideapad S540-14IWL Touch, 14.0\"FHD IPS Glare 1920x1080, Intel Core",
    "currentPrice": 669.99,
    "previousPrice": 0
},
{
    "ID": 0,
    "CreatedAt": "0001-01-01T00:00:00Z",
    "UpdatedAt": "0001-01-01T00:00:00Z",
    "DeletedAt": null,
    "name": "adidas Alphabounce+ Shoes Men's",
    "currentPrice": 0,
    "previousPrice": 0
},
{
    "ID": 0,
    "CreatedAt": "0001-01-01T00:00:00Z",
    "UpdatedAt": "0001-01-01T00:00:00Z",
    "DeletedAt": null,
    "name": "Beaded Cuff Bracelet with Cubic Zirconias in Plated Bronze, 7\"",
    "currentPrice": 18.79,
    "previousPrice": 0
},
{
    "ID": 0,
    "CreatedAt": "0001-01-01T00:00:00Z",
    "UpdatedAt": "0001-01-01T00:00:00Z",
    "DeletedAt": null,
    "name": "Puma Platform Trace Sneakers Casual    - Burgundy - Womens",
    "currentPrice": 27.96,
    "previousPrice": 0
},
{
    "ID": 0,
    "CreatedAt": "0001-01-01T00:00:00Z",
    "UpdatedAt": "0001-01-01T00:00:00Z",
    "DeletedAt": null,
    "name": "Sunforce 100 LED Twin Head Solar Motion Light with Corner Mounting Feature 82112",
    "currentPrice": 29.99,
    "previousPrice": 0
},
{
    "ID": 0,
    "CreatedAt": "0001-01-01T00:00:00Z",
    "UpdatedAt": "0001-01-01T00:00:00Z",
    "DeletedAt": null,
    "name": "Apple AirPods 2 with Charging Case MV7N2AM/A - White",
    "currentPrice": 104.99,
    "previousPrice": 0
},
{
    "ID": 0,
    "CreatedAt": "0001-01-01T00:00:00Z",
    "UpdatedAt": "0001-01-01T00:00:00Z",
    "DeletedAt": null,
    "name": "Dyson V7 Animal + Cordless HEPA Vacuum | Refurbished",
    "currentPrice": 229.99,
    "previousPrice": 0
},
{
    "ID": 0,
    "CreatedAt": "0001-01-01T00:00:00Z",
    "UpdatedAt": "0001-01-01T00:00:00Z",
    "DeletedAt": null,
    "name": "ASICS GEL-Contend 5  Casual Running Stability Shoes - Grey - Mens",
    "currentPrice": 31.96,
    "previousPrice": 0
},
{
    "ID": 0,
    "CreatedAt": "0001-01-01T00:00:00Z",
    "UpdatedAt": "0001-01-01T00:00:00Z",
    "DeletedAt": null,
    "name": "Obsession Cologne by Calvin Klein, 4 oz EDT Spray for Men NEW IN BOX",
    "currentPrice": 20.2,
    "previousPrice": 0
},
{
    "ID": 0,
    "CreatedAt": "0001-01-01T00:00:00Z",
    "UpdatedAt": "0001-01-01T00:00:00Z",
    "DeletedAt": null,
    "name": "DEWALT 5.5 Amp 1 in. Compact Jigsaw Kit DW317KR Recon",
    "currentPrice": 77.99,
    "previousPrice": 0
},
{
    "ID": 0,
    "CreatedAt": "0001-01-01T00:00:00Z",
    "UpdatedAt": "0001-01-01T00:00:00Z",
    "DeletedAt": null,
    "name": "New Taylormade Spider Tour Platinum Putter - Choose Length - Superstroke Grip",
    "currentPrice": 102.99,
    "previousPrice": 0
},
{
    "ID": 0,
    "CreatedAt": "0001-01-01T00:00:00Z",
    "UpdatedAt": "0001-01-01T00:00:00Z",
    "DeletedAt": null,
    "name": "Sony GTK-XB60 High Power Bluetooth Wireless Home Audio System",
    "currentPrice": 129,
    "previousPrice": 0
},
{
    "ID": 0,
    "CreatedAt": "0001-01-01T00:00:00Z",
    "UpdatedAt": "0001-01-01T00:00:00Z",
    "DeletedAt": null,
    "name": "SPECIAL PRICE! 1 oz Gold Eagle Coin (BU Condition) with Stainless Steel Bezel",
    "currentPrice": 0,
    "previousPrice": 0
},
{
    "ID": 0,
    "CreatedAt": "0001-01-01T00:00:00Z",
    "UpdatedAt": "0001-01-01T00:00:00Z",
    "DeletedAt": null,
    "name": "Makita LXT 18V Li-Ion Reciprocating Saw (Tool Only) XRJ04Z-R Reconditioned",
    "currentPrice": 89.99,
    "previousPrice": 0
},
{
    "ID": 0,
    "CreatedAt": "0001-01-01T00:00:00Z",
    "UpdatedAt": "0001-01-01T00:00:00Z",
    "DeletedAt": null,
    "name": "Apple Watch - Series 5 - GPS - 44mm - 1 Year Apple Warranty - Brand New!",
    "currentPrice": 409.99,
    "previousPrice": 0
},
{
    "ID": 0,
    "CreatedAt": "0001-01-01T00:00:00Z",
    "UpdatedAt": "0001-01-01T00:00:00Z",
    "DeletedAt": null,
    "name": "NEW HTC VIVE Virtual Reality System VR Headset",
    "currentPrice": 559,
    "previousPrice": 0
},
{
    "ID": 0,
    "CreatedAt": "0001-01-01T00:00:00Z",
    "UpdatedAt": "0001-01-01T00:00:00Z",
    "DeletedAt": null,
    "name": "Star Wars Force Resistance A-Wing Fighter and Resistance Pilot Tallie Figure",
    "currentPrice": 19.99,
    "previousPrice": 0
},
{
    "ID": 0,
    "CreatedAt": "0001-01-01T00:00:00Z",
    "UpdatedAt": "0001-01-01T00:00:00Z",
    "DeletedAt": null,
    "name": "Apple iPhone 7+ Plus - 32GB 128GB 256GB GSM \"Factory Unlocked\" Smartphone Phone*",
    "currentPrice": 0,
    "previousPrice": 0
},
{
    "ID": 0,
    "CreatedAt": "0001-01-01T00:00:00Z",
    "UpdatedAt": "0001-01-01T00:00:00Z",
    "DeletedAt": null,
    "name": "Powerbuilt 2 in 1, 12 Volt Electric Floor Jack and Tire Inflator, 1 Ton,  620484",
    "currentPrice": 87.99,
    "previousPrice": 0
},
{
    "ID": 0,
    "CreatedAt": "0001-01-01T00:00:00Z",
    "UpdatedAt": "0001-01-01T00:00:00Z",
    "DeletedAt": null,
    "name": "Michael Kors Jet Set Medium Carryall Tote MK Signature Brown Vanilla Pink Black",
    "currentPrice": 87,
    "previousPrice": 0
},
{
    "ID": 0,
    "CreatedAt": "0001-01-01T00:00:00Z",
    "UpdatedAt": "0001-01-01T00:00:00Z",
    "DeletedAt": null,
    "name": "Sony Alpha a7 III Mirrorless Digital Camera (Body Only)  ILCE7M3/B",
    "currentPrice": 0,
    "previousPrice": 0
},
{
    "ID": 0,
    "CreatedAt": "0001-01-01T00:00:00Z",
    "UpdatedAt": "0001-01-01T00:00:00Z",
    "DeletedAt": null,
    "name": "adidas Crazy 8 ADV  Casual Basketball  Shoes - Red - Womens",
    "currentPrice": 47.96,
    "previousPrice": 0
},
{
    "ID": 0,
    "CreatedAt": "0001-01-01T00:00:00Z",
    "UpdatedAt": "0001-01-01T00:00:00Z",
    "DeletedAt": null,
    "name": "KitchenAid Refurbished 3.5 Cup Food Chopper, RKFC3516",
    "currentPrice": 0,
    "previousPrice": 0
},
